descriptive/__init__.py
descriptive/pyeda.py
pydatavisualization-0.0.5.dist-info/LICENSE
pydatavisualization-0.0.5.dist-info/METADATA
pydatavisualization-0.0.5.dist-info/WHEEL
pydatavisualization-0.0.5.dist-info/top_level.txt
pydatavisualization-0.0.5.dist-info/RECORD
