Metadata-Version: 2.1
Name: pydatavisualization
Version: 0.0.5
Summary: Data Visualization Functions
Author: Tamer Samara
Author-email: tamer.samara@gmail.com
License: MIT
Keywords: python,datascience,eda,datapreprocessing,dataanalysis,machinelearning
Classifier: Programming Language :: Python :: 3
Classifier: Operating System :: Unix
Classifier: Operating System :: MacOS :: MacOS X
Classifier: Operating System :: Microsoft :: Windows
License-File: LICENSE
Requires-Dist: Pandas
Requires-Dist: Statsmodels
Requires-Dist: Seaborn
Requires-Dist: Matplotlib
Requires-Dist: NumPy
Requires-Dist: Scikit-learn
